drf_rw_serializers-stubs/__init__.pyi
drf_rw_serializers-stubs/apps.pyi
drf_rw_serializers-stubs/generics.pyi
drf_rw_serializers-stubs/mixins.pyi
drf_rw_serializers-stubs/viewsets.pyi
drf_rw_serializers_stubs-1.0.4.dist-info/WHEEL
drf_rw_serializers_stubs-1.0.4.dist-info/METADATA
drf_rw_serializers_stubs-1.0.4.dist-info/RECORD
